phawd.cpython-39-i386-linux-gnu.so
phawd-0.3.dist-info/LICENSE
phawd-0.3.dist-info/top_level.txt
phawd-0.3.dist-info/WHEEL
phawd-0.3.dist-info/METADATA
phawd-0.3.dist-info/RECORD
