Metadata-Version: 2.1
Name: phawd
Version: 0.3
Summary: python binding for phawd
Home-page: https://github.com/HuNingHe/phawd
Author: HuNing-He
Author-email: 957278968@qq.com
License: MIT
Project-URL: Source Code, https://github.com/HuNingHe/phawd_py
Project-URL: Bug Tracker, https://github.com/HuNingHe/phawd_py/issues
Keywords: phawd python cross-platform c++
Platform: UNKNOWN
Classifier: License :: OSI Approved :: MIT License
Classifier: Programming Language :: C
Classifier: Programming Language :: C++
Classifier: Programming Language :: Python
Classifier: Intended Audience :: Developers
Classifier: Topic :: Scientific/Engineering :: Visualization
Classifier: Typing :: Typed
Requires-Python: >=3.6
License-File: LICENSE
Provides-Extra: test
Requires-Dist: pytest (>=6.0) ; extra == 'test'
